kisa_locations/__init__.py
kisa_locations/uganda.py
kisa_locations/db/EC_Jul2022.sqlite3
kisa_locations/db/locations.ubos.sqlite3
kisa_locations-0.2.6.dist-info/METADATA
kisa_locations-0.2.6.dist-info/WHEEL
kisa_locations-0.2.6.dist-info/top_level.txt
kisa_locations-0.2.6.dist-info/RECORD
