Metadata-Version: 2.1
Name: kisa-locations
Version: 0.2.6
Summary: Locations Utility functions and modules for KISA Developers
Author: Tom Bukenya
Author-email: glayn2bukman@gmail.com
Classifier: Programming Language :: Python :: 3
Classifier: License :: OSI Approved :: MIT License
Classifier: Operating System :: OS Independent
Requires-Python: >=3.11
Requires-Dist: kisa-utils >=0.39.1
